[
  {
    "summary_date": "2022-04-25",
    "period_id": 0,
    "is_longest": 1,
    "timezone": 600,
    "bedtime_end": "2022-04-26T07:18:40+10:00",
    "bedtime_start": "2022-04-26T01:03:40+10:00",
    "breath_average": 16.375,
    "duration": 22500,
    "total": 19230,
    "awake": 3270,
    "rem": 360,
    "deep": 6000,
    "light": 12870,
    "midpoint_time": 10260,
    "efficiency": 85,
    "restless": 20,
    "onset_latency": 150,
    "hr_5min": [
      71,
      69,
      70,
      71,
      71,
      70,
      70,
      68,
      69,
      70,
      69,
      70,
      69,
      70,
      69,
      65,
      66,
      66,
      67,
      67,
      66,
      69,
      64,
      64,
      64,
      63,
      63,
      63,
      63,
      60,
      62,
      63,
      63,
      65,
      63,
      65,
      67,
      66,
      66,
      65,
      63,
      64,
      66,
      70,
      67,
      68,
      67,
      62,
      62,
      63,
      60,
      62,
      62,
      62,
      64,
      58,
      58,
      62,
      66,
      69,
      67,
      68,
      63,
      59,
      57,
      67,
      66,
      0,
      66,
      66,
      58,
      57,
      57,
      57,
      59,
      67
    ],
    "hr_average": 64.93,
    "hr_lowest": 57,
    "hypnogram_5min": "221111112112222221122222222212222212111222121222222221222442312224244242224",
    "rmssd": 44,
    "rmssd_5min": [
      31,
      37,
      31,
      31,
      27,
      27,
      27,
      36,
      24,
      21,
      23,
      27,
      30,
      19,
      41,
      37,
      30,
      31,
      26,
      35,
      33,
      22,
      56,
      44,
      65,
      69,
      64,
      46,
      65,
      91,
      69,
      46,
      50,
      33,
      66,
      48,
      29,
      33,
      27,
      41,
      44,
      34,
      50,
      41,
      54,
      47,
      49,
      66,
      50,
      44,
      66,
      45,
      45,
      48,
      44,
      106,
      123,
      91,
      59,
      35,
      42,
      48,
      103,
      101,
      110,
      41,
      41,
      0,
      47,
      59,
      115,
      117,
      103,
      106,
      93,
      68
    ],
    "score": 60,
    "score_alignment": 72,
    "score_deep": 95,
    "score_disturbances": 73,
    "score_efficiency": 83,
    "score_latency": 67,
    "score_rem": 5,
    "score_total": 48,
    "temperature_deviation": 0.05,
    "temperature_trend_deviation": 0.32,
    "bedtime_start_delta": 3820,
    "bedtime_end_delta": 26320,
    "midpoint_at_delta": 14080,
    "temperature_delta": 0.05
  }
]