{
  "1": {
    "total": 18450,
    "rem": 1110,
    "awake": 8070,
    "deep": 1560,
    "duration": 26520,
    "efficiency": 70,
    "light": 15780,
    "score": 34
  },
  "2": {},
  "3": {
    "total": 32550,
    "rem": 5970,
    "awake": 6750,
    "deep": 6330,
    "duration": 39300,
    "efficiency": 83,
    "light": 20250,
    "score": 84
  },
  "4": {
    "total": 33270,
    "rem": 6840,
    "awake": 4830,
    "deep": 7530,
    "duration": 38100,
    "efficiency": 87,
    "light": 18900,
    "score": 80
  },
  "5": {
    "total": 23040,
    "rem": 3480,
    "awake": 3540,
    "deep": 6030,
    "duration": 26580,
    "efficiency": 87,
    "light": 13530,
    "score": 66
  },
  "6": {
    "total": 30720,
    "rem": 2400,
    "awake": 4140,
    "deep": 9180,
    "duration": 34860,
    "efficiency": 88,
    "light": 19140,
    "score": 74
  },
  "7": {
    "total": 18960,
    "rem": 1260,
    "awake": 2280,
    "deep": 6900,
    "duration": 21240,
    "efficiency": 89,
    "light": 10800,
    "score": 57
  },
  "8": {
    "total": 23190,
    "rem": 2310,
    "awake": 2550,
    "deep": 10050,
    "duration": 25740,
    "efficiency": 90,
    "light": 10830,
    "score": 65
  },
  "9": {
    "total": 20940,
    "rem": 1170,
    "awake": 2460,
    "deep": 8490,
    "duration": 23400,
    "efficiency": 89,
    "light": 11280,
    "score": 61
  },
  "10": {
    "total": 22410,
    "rem": 2190,
    "awake": 2310,
    "deep": 8130,
    "duration": 24720,
    "efficiency": 91,
    "light": 12090,
    "score": 69
  },
  "11": {
    "total": 22470,
    "rem": 2220,
    "awake": 11130,
    "deep": 4710,
    "duration": 33600,
    "efficiency": 67,
    "light": 15540,
    "score": 53
  },
  "12": {
    "total": 27300,
    "rem": 11610,
    "awake": 10080,
    "deep": 5550,
    "duration": 37380,
    "efficiency": 73,
    "light": 10140,
    "score": 70
  },
  "13": {
    "total": 27990,
    "rem": 2790,
    "awake": 5550,
    "deep": 6240,
    "duration": 33540,
    "efficiency": 83,
    "light": 18960,
    "score": 70
  },
  "14": {
    "total": 15390,
    "rem": 60,
    "awake": 5190,
    "deep": 4470,
    "duration": 20580,
    "efficiency": 75,
    "light": 10860,
    "score": 45
  },
  "15": {
    "total": 22200,
    "rem": 330,
    "awake": 5700,
    "deep": 8880,
    "duration": 27900,
    "efficiency": 80,
    "light": 12990,
    "score": 58
  },
  "16": {
    "total": 20910,
    "rem": 4050,
    "awake": 6510,
    "deep": 4200,
    "duration": 27420,
    "efficiency": 76,
    "light": 12660,
    "score": 56
  },
  "17": {
    "total": 28740,
    "rem": 4470,
    "awake": 5700,
    "deep": 5610,
    "duration": 34440,
    "efficiency": 83,
    "light": 18660,
    "score": 72
  },
  "18": {
    "total": 13650,
    "rem": 840,
    "awake": 1230,
    "deep": 7440,
    "duration": 14880,
    "efficiency": 92,
    "light": 5370,
    "score": 54
  },
  "19": {},
  "20": {
    "total": 43200,
    "rem": 8670,
    "awake": 10800,
    "deep": 6450,
    "duration": 54000,
    "efficiency": 80,
    "light": 28080,
    "score": 80
  },
  "21": {},
  "22": {
    "total": 22830,
    "rem": 3540,
    "awake": 5070,
    "deep": 9480,
    "duration": 27900,
    "efficiency": 82,
    "light": 9810,
    "score": 64
  },
  "23": {
    "total": 16500,
    "rem": 1950,
    "awake": 6840,
    "deep": 4740,
    "duration": 23340,
    "efficiency": 71,
    "light": 9810,
    "score": 46
  },
  "24": {},
  "25": {},
  "26": {},
  "27": {},
  "28": {},
  "29": {},
  "30": {}
}