[
  {
    "summary_date": "2022-06-17",
    "period_id": 0,
    "is_longest": 1,
    "timezone": 600,
    "bedtime_end": "2022-06-18T08:55:02+10:00",
    "bedtime_start": "2022-06-18T01:52:02+10:00",
    "breath_average": 16.75,
    "duration": 25380,
    "total": 22980,
    "awake": 2400,
    "rem": 3570,
    "deep": 11130,
    "light": 8280,
    "midpoint_time": 12720,
    "efficiency": 91,
    "restless": 18,
    "onset_latency": 420,
    "hr_5min": [
      0,
      0,
      85,
      87,
      88,
      89,
      89,
      89,
      89,
      89,
      89,
      89,
      85,
      86,
      85,
      85,
      85,
      86,
      0,
      0,
      0,
      83,
      85,
      83,
      84,
      81,
      77,
      77,
      79,
      78,
      78,
      77,
      77,
      76,
      78,
      79,
      80,
      80,
      80,
      81,
      81,
      79,
      80,
      79,
      80,
      77,
      80,
      81,
      78,
      79,
      79,
      78,
      76,
      77,
      79,
      79,
      79,
      79,
      77,
      77,
      73,
      76,
      77,
      76,
      75,
      72,
      70,
      69,
      72,
      71,
      72,
      72,
      70,
      68,
      71,
      69,
      67,
      68,
      71,
      69,
      69,
      71,
      72,
      71,
      0
    ],
    "hr_average": 78.39,
    "hr_lowest": 67,
    "hypnogram_5min": "4411111121111122222111111422311322111111122111233333111111222211222333333222222222244",
    "rmssd": 22,
    "rmssd_5min": [
      0,
      0,
      15,
      10,
      9,
      8,
      8,
      7,
      7,
      7,
      7,
      9,
      15,
      15,
      10,
      11,
      11,
      11,
      0,
      0,
      0,
      18,
      19,
      14,
      13,
      20,
      31,
      22,
      15,
      16,
      15,
      17,
      17,
      16,
      15,
      15,
      14,
      15,
      14,
      15,
      14,
      25,
      17,
      24,
      16,
      34,
      25,
      36,
      32,
      19,
      17,
      18,
      18,
      16,
      14,
      14,
      15,
      26,
      20,
      25,
      34,
      22,
      20,
      24,
      39,
      59,
      33,
      46,
      31,
      48,
      16,
      17,
      23,
      45,
      39,
      59,
      65,
      52,
      37,
      54,
      59,
      57,
      48,
      56,
      0
    ],
    "score": 68,
    "score_alignment": 27,
    "score_deep": 100,
    "score_disturbances": 72,
    "score_efficiency": 96,
    "score_latency": 78,
    "score_rem": 48,
    "score_total": 63,
    "temperature_deviation": -0.52,
    "temperature_trend_deviation": -0.31,
    "bedtime_start_delta": 6722,
    "bedtime_end_delta": 32102,
    "midpoint_at_delta": 19442,
    "temperature_delta": -0.52
  }
]